hgvs2seq/__init__.py
hgvs2seq/ascii.py
hgvs2seq/hgvs2seq.py
hgvs2seq/info.py
hgvs2seq/query.py
hgvs2seq/sequences.py
hgvs2seq/usage.py
hgvs2seq-0.2.0b0.dist-info/licenses/LICENCE.md
hgvs2seq-0.2.0b0.dist-info/METADATA
hgvs2seq-0.2.0b0.dist-info/WHEEL
hgvs2seq-0.2.0b0.dist-info/entry_points.txt
hgvs2seq-0.2.0b0.dist-info/top_level.txt
hgvs2seq-0.2.0b0.dist-info/RECORD
