Metadata-Version: 2.4
Name: hgvs2seq
Version: 0.2.0b0
Summary: From table file containing HGVS column, it returns a fixed size sequence
Home-page: https://github.com/bio2m/hgvs2seq
Author: Benoit Guibert
Author-email: benoit.guibert@free.fr
License: GPLv3
Classifier: Development Status :: 3 - Alpha
Classifier: License :: OSI Approved :: GNU General Public License v3 (GPLv3)
Classifier: Operating System :: POSIX :: Linux
Classifier: Natural Language :: English
Classifier: Intended Audience :: Science/Research
Requires-Python: >=3.7
License-File: LICENCE.md
Requires-Dist: biopython
Dynamic: author
Dynamic: author-email
Dynamic: classifier
Dynamic: description
Dynamic: description-content-type
Dynamic: home-page
Dynamic: license
Dynamic: license-file
Dynamic: requires-dist
Dynamic: requires-python
Dynamic: summary
